iuser_i18n/__init__.py
iuser_i18n/__main__.py
iuser_i18n/base.py
iuser_i18n-0.0.2.data/scripts/i18n
iuser_i18n-0.0.2.dist-info/LICENSE
iuser_i18n-0.0.2.dist-info/METADATA
iuser_i18n-0.0.2.dist-info/WHEEL
iuser_i18n-0.0.2.dist-info/top_level.txt
iuser_i18n-0.0.2.dist-info/RECORD
