Metadata-Version: 2.1
Name: iuser-i18n
Version: 0.0.2
Summary: iuser_i18n
Home-page: https://github.com/iuser-dev/iuser-i18n-translate/
Author: iuser
Author-email: iuser.link@gmail.com
License-File: LICENSE
Requires-Dist: volcengine
